sfu_data_io/__init__.py
sfu_data_io/helpers.py
sfu_data_io-0.1.7.dist-info/LICENSE
sfu_data_io-0.1.7.dist-info/WHEEL
sfu_data_io-0.1.7.dist-info/METADATA
sfu_data_io-0.1.7.dist-info/RECORD
